volcano/core/__init__.py
volcano/core/__main__.py
volcano/core/connection.py
volcano/core/cp.py
volcano/core/cvt.py
volcano/core/db.py
volcano/core/demo.xml
volcano/core/errors.py
volcano/core/expr.py
volcano/core/msg_parser.py
volcano_core-0.4.9.dist-info/LICENSE
volcano_core-0.4.9.dist-info/METADATA
volcano_core-0.4.9.dist-info/WHEEL
volcano_core-0.4.9.dist-info/top_level.txt
volcano_core-0.4.9.dist-info/RECORD
