Metadata-Version: 2.1
Name: volcano-core
Version: 0.4.9
Summary: Volcano on Python
Home-page: UNKNOWN
Author: Vinogradov D
Author-email: dgrapes@gmail.com
License: MIT
Platform: UNKNOWN
Classifier: Programming Language :: Python :: 3
Classifier: License :: OSI Approved :: MIT License
Classifier: Operating System :: OS Independent
Requires-Dist: volcano-general
Requires-Dist: twisted
